awslabs/__init__.py
awslabs/aws_security_hub_mcp_server/__init__.py
awslabs_aws_security_hub_mcp_server-0.0.0.dist-info/METADATA
awslabs_aws_security_hub_mcp_server-0.0.0.dist-info/WHEEL
awslabs_aws_security_hub_mcp_server-0.0.0.dist-info/licenses/LICENSE
awslabs_aws_security_hub_mcp_server-0.0.0.dist-info/licenses/NOTICE
awslabs_aws_security_hub_mcp_server-0.0.0.dist-info/RECORD
